beta4parlbe/__init__.py
beta4parlbe/beta4parlbe.py
beta4parmom/__init__.py
beta4parmom/beta4parmom.py
beta4parprop/__init__.py
beta4parprop/beta4parprop.py
py_4parbeta-0.0.1.dist-info/METADATA
py_4parbeta-0.0.1.dist-info/WHEEL
py_4parbeta-0.0.1.dist-info/top_level.txt
py_4parbeta-0.0.1.dist-info/RECORD
